csv_too_json-0.0.5.dist-info/WHEEL
csv_too_json-0.0.5.dist-info/top_level.txt
csv_too_json-0.0.5.dist-info/DESCRIPTION.rst
csv_too_json-0.0.5.dist-info/RECORD
csv_too_json-0.0.5.dist-info/metadata.json
csv_too_json-0.0.5.dist-info/METADATA
csv__too__json/__init__.py
csv__too__json/example.py
